monotonic_time.py
monotonic_time-2.1.0.dist-info/DESCRIPTION.rst
monotonic_time-2.1.0.dist-info/METADATA
monotonic_time-2.1.0.dist-info/RECORD
monotonic_time-2.1.0.dist-info/WHEEL
monotonic_time-2.1.0.dist-info/metadata.json
monotonic_time-2.1.0.dist-info/top_level.txt
