Metadata-Version: 2.0
Name: monotonic-time
Version: 2.1.0
Summary: monotonic time for Python 2 and 3, on Linux, FreeBSD, Mac OS X, and Windows.
Home-page: https://github.com/gavinbeatty/python-monotonic-time
Author: Gavin Beatty
Author-email: gavinbeatty@gmail.com
License: MIT
Keywords: monotonic,time,clock
Platform: any
Classifier: Natural Language :: English
Classifier: Development Status :: 4 - Beta
Classifier: License :: OSI Approved :: MIT License
Classifier: Programming Language :: Python :: 2
Classifier: Programming Language :: Python :: 3
Classifier: Operating System :: MacOS :: MacOS X
Classifier: Operating System :: POSIX :: Linux
Classifier: Operating System :: POSIX :: BSD :: FreeBSD
Classifier: Operating System :: Microsoft :: Windows
